firefly_auth_middleware/__init__.py
firefly_auth_middleware/application/__init__.py
firefly_auth_middleware/application/middleware.py
firefly_auth_middleware/domain/__init__.py
firefly_auth_middleware/infrastructure/__init__.py
firefly_auth_middleware/presentation/__init__.py
firefly_auth_middleware-0.1.7.dist-info/METADATA
firefly_auth_middleware-0.1.7.dist-info/WHEEL
firefly_auth_middleware-0.1.7.dist-info/entry_points.txt
firefly_auth_middleware-0.1.7.dist-info/top_level.txt
firefly_auth_middleware-0.1.7.dist-info/RECORD
